ipyfastscape/__init__.py
ipyfastscape/common.py
ipyfastscape/topoviz3d.py
ipyfastscape/xr_accessor.py
ipyfastscape/tests/__init__.py
ipyfastscape/tests/conftest.py
ipyfastscape/tests/test_common.py
ipyfastscape/tests/test_topoviz3d.py
ipyfastscape/tests/test_xr_accessor.py
ipyfastscape/tests/utils.py
ipyfastscape-0.2.1.dist-info/LICENSE
ipyfastscape-0.2.1.dist-info/METADATA
ipyfastscape-0.2.1.dist-info/WHEEL
ipyfastscape-0.2.1.dist-info/top_level.txt
ipyfastscape-0.2.1.dist-info/RECORD
