Metadata-Version: 2.1
Name: ipyfastscape
Version: 0.2.1
Summary: Interactive widgets for topographic data analysis and modelling in Jupyter notebooks
Author-email: Benoît Bovy <benbovy@gmail.com>
Maintainer: IpyFastscape contributors
License: BSD-3-Clause
Project-URL: Repository, https://github.com/fastscape-lem/ipyfastscape
Keywords: fastscape,xarray,jupyter,landscape,topography
Classifier: Intended Audience :: Science/Research
Classifier: License :: OSI Approved :: BSD License
Classifier: Operating System :: OS Independent
Classifier: Programming Language :: Python :: 3
Requires-Python: >=3.9
License-File: LICENSE
Requires-Dist: xarray
Requires-Dist: ipywidgets
Requires-Dist: ipygany >=0.5.0
Provides-Extra: dev
Requires-Dist: pytest ; extra == 'dev'
